trsolverscraper/__init__.py
trsolverscraper/cloudflare.py
trsolverscraper/exceptions.py
trsolverscraper/help.py
trsolverscraper/trscraper.py
trsolverscraper/captcha/__init__.py
trsolverscraper/interpreters/__init__.py
trsolverscraper/interpreters/chakracore.py
trsolverscraper/interpreters/encapsulated.py
trsolverscraper/interpreters/js2py.py
trsolverscraper/interpreters/jsunfuck.py
trsolverscraper/interpreters/native.py
trsolverscraper/interpreters/nodejs.py
trsolverscraper/interpreters/v8.py
trsolverscraper/user_agent/__init__.py
trsolverscraper-1.2.78.dist-info/METADATA
trsolverscraper-1.2.78.dist-info/WHEEL
trsolverscraper-1.2.78.dist-info/top_level.txt
trsolverscraper-1.2.78.dist-info/RECORD
